label_studio/.coveragerc
label_studio/__init__.py
label_studio/annotation_templates/CONTRIBUTING.md
label_studio/annotation_templates/README.md
label_studio/annotation_templates/audio-speech-processing/automatic-speech-recognition/config.xml
label_studio/annotation_templates/audio-speech-processing/automatic-speech-recognition/config.yml
label_studio/annotation_templates/audio-speech-processing/automatic-speech-recognition-using-segments/config.xml
label_studio/annotation_templates/audio-speech-processing/automatic-speech-recognition-using-segments/config.yml
label_studio/annotation_templates/audio-speech-processing/conversational-analysis/config.yml
label_studio/annotation_templates/audio-speech-processing/intent-classification/config.xml
label_studio/annotation_templates/audio-speech-processing/intent-classification/config.yml
label_studio/annotation_templates/audio-speech-processing/signal-quality-detection/config.xml
label_studio/annotation_templates/audio-speech-processing/signal-quality-detection/config.yml
label_studio/annotation_templates/audio-speech-processing/sound-event-detection/config.xml
label_studio/annotation_templates/audio-speech-processing/sound-event-detection/config.yml
label_studio/annotation_templates/audio-speech-processing/speaker-segmentation/config.xml
label_studio/annotation_templates/audio-speech-processing/speaker-segmentation/config.yml
label_studio/annotation_templates/audio-speech-processing/speech-transcription/config.yml
label_studio/annotation_templates/computer-vision/image-captioning/config.yml
label_studio/annotation_templates/computer-vision/image-classification/config.yml
label_studio/annotation_templates/computer-vision/inventory-tracking/config.yml
label_studio/annotation_templates/computer-vision/keypoints/config.yml
label_studio/annotation_templates/computer-vision/multipage-documents/config.xml
label_studio/annotation_templates/computer-vision/multipage-documents/config.yml
label_studio-1.12.0.post0.dist-info/LICENSE
label_studio-1.12.0.post0.dist-info/METADATA
label_studio-1.12.0.post0.dist-info/NOTICE
label_studio-1.12.0.post0.dist-info/WHEEL
label_studio-1.12.0.post0.dist-info/entry_points.txt
label_studio-1.12.0.post0.dist-info/RECORD
