Metadata-Version: 2.1
Name: label-studio
Version: 1.12.0.post0
Summary: Label Studio annotation tool
Home-page: https://github.com/heartexlabs/label-studio
License: Apache-2.0
Author: Heartex
Author-email: hello@heartex.ai
Requires-Python: >=3.8,<4
Classifier: License :: OSI Approved :: Apache Software License
Classifier: Operating System :: OS Independent
Classifier: Programming Language :: Python :: 3
Classifier: Programming Language :: Python :: 3.8
Classifier: Programming Language :: Python :: 3.9
Classifier: Programming Language :: Python :: 3.10
Classifier: Programming Language :: Python :: 3.11
Classifier: Programming Language :: Python :: 3.12
Provides-Extra: mysql
Requires-Dist: Django (>=3.2.24,<3.3.0)
Requires-Dist: appdirs (>=1.4.3)
Requires-Dist: attr (==0.3.1)
Requires-Dist: attrs (>=19.2.0)
Requires-Dist: azure-storage-blob (>=12.6.0)
Requires-Dist: bleach (>=5.0.0,<5.1.0)
Requires-Dist: boto (>=2.49.0,<3.0.0)
Requires-Dist: boto3 (>=1.28.58,<2.0.0)
Requires-Dist: botocore (>=1.31.58,<2.0.0)
Requires-Dist: boxing (>=0.1.4)
Requires-Dist: colorama (>=0.4.4)
Requires-Dist: defusedxml (>=0.7.1)
Requires-Dist: django-annoying (==0.10.6)
Requires-Dist: django-cors-headers (==3.6.0)
Requires-Dist: django-csp (==3.7)
Requires-Dist: django-debug-toolbar (==3.2.1)
Requires-Dist: django-environ (==0.10.0)
Requires-Dist: django-extensions (==3.1.0)
Requires-Dist: django-filter (==2.4.0)
Requires-Dist: django-model-utils (==4.1.1)
Requires-Dist: django-ranged-fileresponse (>=0.1.2)
Requires-Dist: django-rq (==2.5.1)
Requires-Dist: django-storages (==1.12.3)
Requires-Dist: django-user-agents (==0.4.0)
Requires-Dist: djangorestframework (==3.13.1)
Requires-Dist: drf-dynamic-fields (==0.3.0)
Requires-Dist: drf-flex-fields (==0.9.5)
Requires-Dist: drf-generators (==0.3.0)
Requires-Dist: google-cloud-logging (>=3.10.0,<4.0.0)
Requires-Dist: google-cloud-storage (>=2.13.0,<3.0.0)
Requires-Dist: htmlmin (==0.1.12)
Requires-Dist: humansignal-drf-yasg (>=1.21.9)
Requires-Dist: jsonschema (==3.2.0)
Requires-Dist: label-studio-converter (==0.0.58)
Requires-Dist: launchdarkly-server-sdk (==8.2.1)
Requires-Dist: lockfile (>=0.12.0)
Requires-Dist: lxml (>=4.2.5)
Requires-Dist: mysqlclient ; extra == "mysql"
Requires-Dist: numpy (>=1.24.3,<2.0.0)
Requires-Dist: openai (>=1.10.0,<2.0.0)
Requires-Dist: ordered-set (==4.0.2)
Requires-Dist: pandas (>=0.24.0)
Requires-Dist: psycopg2-binary (==2.9.6)
Requires-Dist: pydantic (>=1.7.3,<=1.11.0)
Requires-Dist: python-dateutil (>=2.8.1)
Requires-Dist: python-json-logger (==2.0.4)
Requires-Dist: pytz (>=2022.1,<2023.0)
Requires-Dist: pyyaml (>=6.0.0)
Requires-Dist: redis (>=3.5,<4.0)
Requires-Dist: requests (==2.31.0)
Requires-Dist: rq (==1.10.1)
Requires-Dist: rules (==2.2)
Requires-Dist: sentry-sdk (>=1.1.0)
Requires-Dist: ujson (>=3.0.0)
Requires-Dist: urllib3 (>=1.26.18,<2.0.0)
Requires-Dist: wheel (>=0.38.1,<=0.40.0)
Requires-Dist: xmljson (==0.2.0)
